algomancy_scenario/__init__.py
algomancy_scenario/algorithmfactory.py
algomancy_scenario/basealgorithm.py
algomancy_scenario/core_configuration.py
algomancy_scenario/keyperformanceindicator.py
algomancy_scenario/kpifactory.py
algomancy_scenario/py.typed
algomancy_scenario/result.py
algomancy_scenario/scenario.py
algomancy_scenario/scenariofactory.py
algomancy_scenario/scenariomanager.py
algomancy_scenario/scenarioprocessor.py
algomancy_scenario/scenarioregistry.py
algomancy_scenario-0.3.18.dist-info/WHEEL
algomancy_scenario-0.3.18.dist-info/METADATA
algomancy_scenario-0.3.18.dist-info/RECORD
