Metadata-Version: 2.3
Name: algomancy-scenario
Version: 0.3.18
Summary: Scenario management model for the Algomancy library
Author: Pepijn Wissing
Author-email: Pepijn Wissing <Wsg@cqm.nl>
Requires-Dist: algomancy-utils
Requires-Dist: algomancy-data
Requires-Dist: strenum>=0.4.15
Requires-Python: >=3.14
